lektor_treeify.py
lektor_treeify-1.2.dist-info/METADATA
lektor_treeify-1.2.dist-info/WHEEL
lektor_treeify-1.2.dist-info/entry_points.txt
lektor_treeify-1.2.dist-info/top_level.txt
lektor_treeify-1.2.dist-info/RECORD
